runnb/__init__.py
runnb/runnb.py
runnb/tee.py
runnb-1.0.2.dist-info/LICENSE
runnb-1.0.2.dist-info/METADATA
runnb-1.0.2.dist-info/WHEEL
runnb-1.0.2.dist-info/entry_points.txt
runnb-1.0.2.dist-info/top_level.txt
runnb-1.0.2.dist-info/RECORD
