Metadata-Version: 2.1
Name: runnb
Version: 1.0.2
Summary: A lean utility to run the jupyter notebooks from commandline with stdout outputs
Home-page: https://github.com/InnovArul/runnb
Author: Arulkumar along with @guoquan/github
Author-email: arul.csecit@ymail.com
License: UNKNOWN
Project-URL: Source, https://github.com/InnovArul/runnb
Keywords: jupyter notebook
Platform: UNKNOWN
Classifier: Development Status :: 3 - Alpha
Classifier: Intended Audience :: Developers
Classifier: Topic :: Software Development :: Build Tools
Classifier: License :: OSI Approved :: MIT License
Classifier: Programming Language :: Python :: 2
Classifier: Programming Language :: Python :: 2.7
Classifier: Programming Language :: Python :: 3
Classifier: Programming Language :: Python :: 3.4
Classifier: Programming Language :: Python :: 3.5
Classifier: Programming Language :: Python :: 3.6
Classifier: Programming Language :: Python :: 3.7
Requires-Python: >=2.7, !=3.0.*, !=3.1.*, !=3.2.*, !=3.3.*, <4
